elonify/__init__.py
elonify/core.py
elonify-0.0.2.dist-info/METADATA
elonify-0.0.2.dist-info/WHEEL
elonify-0.0.2.dist-info/license
elonify-0.0.2.dist-info/top_level.txt
elonify-0.0.2.dist-info/RECORD
