Metadata-Version: 2.1
Name: elonify
Version: 0.0.2
Summary: The one-liner web toolkit that auto-thinks like Elon.
Home-page: https://github.com/abrlake/elonify
Author: Legen
License: MIT
Project-URL: Homepage, https://github.com/abrlake/elonify
Requires-Python: >=3.7
License-File: license
Requires-Dist: requests
Requires-Dist: beautifulsoup4
